{"id": "81ed939e-dd00-4d12-b7f4-7e9386be5932", "status": "closed", "reference": "58020", "number": 121, "scheduled": "2019-10-29T00:15:00+00:00", "attendance": 59244, "utc_offset": -5, "entry_mode": "INGEST", "weather": "Clear Temp: 59 F, Humidity: 50%, Wind: From NE 2 mph", "clock": "00:00", "quarter": 4, "sr_id": "sr:match:18001513", "summary": {"season": {"id": "19c4ee6a-c1e5-4346-9ef8-1361f81e6716", "year": 2019, "type": "REG", "name": "REG"}, "week": {"id": "61611f1f-5b7a-4925-a054-b8997356e09e", "sequence": 8, "title": "8"}, "venue": {"id": "7349a2e6-0ac9-410b-8bd2-ca58c9f7aa34", "name": "Heinz Field", "city": "Pittsburgh", "state": "PA", "country": "USA", "zip": "15212", "address": "100 Art Rooney Avenue", "capacity": 68400, "surface": "turf", "roof_type": "outdoor", "sr_id": "sr:venue:8197"}, "home": {"id": "cb2f9f1f-ac67-424e-9e72-1475cb0ed398", "name": "Steelers", "market": "Pittsburgh", "alias": "PIT", "reference": "5102", "sr_id": "sr:competitor:4345", "used_timeouts": 1, "remaining_timeouts": 2, "points": 27}, "away": {"id": "4809ecb0-abd3-451d-9c4a-92a90b83ca06", "name": "Dolphins", "market": "Miami", "alias": "MIA", "reference": "5094", "sr_id": "sr:competitor:4287", "used_timeouts": 3, "remaining_timeouts": 0, "points": 14}}, "statistics": {"home": {"id": "cb2f9f1f-ac67-424e-9e72-1475cb0ed398", "name": "Steelers", "market": "Pittsburgh", "alias": "PIT", "reference": "5102", "sr_id": "sr:competitor:4345", "summary": {"possession_time": "35:18", "avg_gain": 5.9, "safeties": 0, "turnovers": 1, "play_count": 67, "rush_plays": 29, "total_yards": 394, "fumbles": 1, "lost_fumbles": 0, "penalties": 9, "penalty_yards": 70, "return_yards": 8}, "rushing": {"totals": {"avg_yards": 5.4, "attempts": 29, "touchdowns": 1, "tlost": 3, "tlost_yards": -3, "yards": 158, "longest": 25, "longest_touchdown": 9, "redzone_attempts": 1, "broken_tackles": 2, "kneel_downs": 0, "scrambles": 0, "yards_after_contact": 72}, "players": [{"id": "9b4e4d1d-ad88-4c10-b1c0-b9116755c184", "name": "Trey Edmunds", "jersey": "33", "reference": "00-0033838", "position": "TE", "sr_id": "sr:player:1135277", "avg_yards": 0.0, "attempts": 1, "touchdowns": 0, "yards": 0, "longest": 0, "longest_touchdown": 0, "redzone_attempts": 0, "tlost": 0, "tlost_yards": 0, "broken_tackles": 0, "kneel_downs": 0, "scrambles": 0, "yards_after_contact": 0}, {"id": "74af3906-083e-49d1-b8c6-556101390381", "name": "Benny Snell Jr.", "jersey": "24", "reference": "00-0035217", "position": "RB", "sr_id": "sr:player:1734857", "avg_yards": 2.6, "attempts": 5, "touchdowns": 0, "yards": 13, "longest": 5, "longest_touchdown": 0, "redzone_attempts": 0, "tlost": 0, "tlost_yards": 0, "broken_tackles": 1, "kneel_downs": 0, "scrambles": 0, "yards_after_contact": 6}, {"id": "28a084c0-14df-499f-bd1f-b975603626b7", "name": "James Conner", "jersey": "30", "reference": "00-0033553", "position": "RB", "sr_id": "sr:player:1129821", "avg_yards": 6.3, "attempts": 23, "touchdowns": 1, "yards": 145, "longest": 25, "longest_touchdown": 9, "redzone_attempts": 1, "tlost": 3, "tlost_yards": -3, "broken_tackles": 1, "kneel_downs": 0, "scrambles": 0, "yards_after_contact": 66}]}, "receiving": {"totals": {"targets": 36, "receptions": 20, "avg_yards": 12.55, "yards": 251, "touchdowns": 2, "yards_after_catch": 100, "longest": 45, "longest_touchdown": 45, "redzone_targets": 3, "air_yards": 151, "broken_tackles": 2, "dropped_passes": 1, "catchable_passes": 1, "yards_after_contact": 24}, "players": [{"id": "f404283a-7c04-4a1c-899c-3243424a8d70", "name": "Donte Moncrief", "jersey": "11", "reference": "00-0031339", "position": "WR", "sr_id": "sr:player:828737", "receptions": 0, "targets": 2, "yards": 0, "avg_yards": 0.0, "longest": 0, "touchdowns": 0, "longest_touchdown": 0, "yards_after_catch": 0, "redzone_targets": 0, "air_yards": 0, "broken_tackles": 0, "dropped_passes": 0, "catchable_passes": 0, "yards_after_contact": 0}, {"id": "28a084c0-14df-499f-bd1f-b975603626b7", "name": "James Conner", "jersey": "30", "reference": "00-0033553", "position": "RB", "sr_id": "sr:player:1129821", "receptions": 3, "targets": 4, "yards": 5, "avg_yards": 1.7, "longest": 9, "touchdowns": 0, "longest_touchdown": 0, "yards_after_catch": 12, "redzone_targets": 1, "air_yards": -7, "broken_tackles": 1, "dropped_passes": 0, "catchable_passes": 0, "yards_after_contact": 9}, {"id": "8f24a248-b328-43ec-8677-67600e42a8f7", "name": "Vance McDonald", "jersey": "89", "reference": "00-0030470", "position": "TE", "sr_id": "sr:player:831385", "receptions": 3, "targets": 4, "yards": 19, "avg_yards": 6.3, "longest": 14, "touchdowns": 0, "longest_touchdown": 0, "yards_after_catch": 7, "redzone_targets": 1, "air_yards": 12, "broken_tackles": 0, "dropped_passes": 0, "catchable_passes": 0, "yards_after_contact": 0}, {"id": "814aa074-fc61-4649-b7a1-098bd3a199fd", "name": "James Washington", "jersey": "13", "reference": "00-0034676", "position": "WR", "sr_id": "sr:player:1473908", "receptions": 1, "targets": 6, "yards": 21, "avg_yards": 21.0, "longest": 21, "touchdowns": 0, "longest_touchdown": 0, "yards_after_catch": 2, "redzone_targets": 0, "air_yards": 19, "broken_tackles": 0, "dropped_passes": 1, "catchable_passes": 1, "yards_after_contact": 0}, {"id": "c731aa8a-778b-4ccd-a19f-517eb66f47b7", "name": "Nick Vannett", "jersey": "88", "reference": "00-0032394", "position": "TE", "sr_id": "sr:player:1074050", "receptions": 1, "targets": 2, "yards": 15, "avg_yards": 15.0, "longest": 15, "touchdowns": 0, "longest_touchdown": 0, "yards_after_catch": 14, "redzone_targets": 0, "air_yards": 1, "broken_tackles": 0, "dropped_passes": 0, "catchable_passes": 0, "yards_after_contact": 0}, {"id": "244c00c7-fe9a-4f4f-adff-1d5b9c8877e7", "name": "Diontae Johnson", "jersey": "18", "reference": "00-0035216", "position": "WR", "sr_id": "sr:player:1221954", "receptions": 5, "targets": 7, "yards": 84, "avg_yards": 16.8, "longest": 45, "touchdowns": 1, "longest_touchdown": 45, "yards_after_catch": 43, "redzone_targets": 0, "air_yards": 41, "broken_tackles": 1, "dropped_passes": 0, "catchable_passes": 0, "yards_after_contact": 12}, {"id": "9547fbb1-0d4f-4d9e-83b9-e2fa30463bb9", "name": "JuJu Smith-Schuster", "jersey": "19", "reference": "00-0033857", "position": "WR", "sr_id": "sr:player:1129761", "receptions": 5, "targets": 9, "yards": 103, "avg_yards": 20.6, "longest": 34, "touchdowns": 1, "longest_touchdown": 26, "yards_after_catch": 13, "redzone_targets": 1, "air_yards": 90, "broken_tackles": 0, "dropped_passes": 0, "catchable_passes": 0, "yards_after_contact": 3}, {"id": "f611f87a-1e49-4196-9088-8c760f26006d", "name": "Roosevelt Nix", "jersey": "45", "reference": "00-0030741", "position": "FB", "sr_id": "sr:player:828561", "receptions": 2, "targets": 2, "yards": 4, "avg_yards": 2.0, "longest": 4, "touchdowns": 0, "longest_touchdown": 0, "yards_after_catch": 9, "redzone_targets": 0, "air_yards": -5, "broken_tackles": 0, "dropped_passes": 0, "catchable_passes": 0, "yards_after_contact": 0}]}, "punts": {"totals": {"attempts": 3, "yards": 140, "net_yards": 105, "blocked": 0, "touchbacks": 0, "inside_20": 0, "return_yards": 35, "avg_net_yards": 35.0, "avg_yards": 46.7, "longest": 49, "hang_time": 13.801000000000002, "avg_hang_time": 4.6}, "players": [{"id": "e20a7609-8129-400f-87b9-d11dda3836b4", "name": "Jordan Berry", "jersey": "04", "reference": "00-0031502", "position": "P", "sr_id": "sr:player:827745", "attempts": 3, "yards": 140, "avg_yards": 46.7, "blocked": 0, "longest": 49, "touchbacks": 0, "inside_20": 0, "avg_net_yards": 35.0, "return_yards": 35, "net_yards": 105, "hang_time": 13.801000000000002, "avg_hang_time": 4.6}]}, "punt_returns": {"totals": {"avg_yards": 2.0, "yards": 2, "longest": 2, "touchdowns": 0, "longest_touchdown": 0, "faircatches": 0, "number": 1}, "players": [{"id": "6259f62d-e16f-4369-a3be-ca02f79f3026", "name": "Ryan Switzer", "jersey": "10", "reference": "00-0033562", "position": "WR", "sr_id": "sr:player:1130155", "yards": 2, "avg_yards": 2.0, "touchdowns": 0, "longest": 2, "faircatches": 0, "longest_touchdown": 0, "number": 1}]}, "penalties": {"totals": {"penalties": 9, "yards": 70}, "players": [{"id": "8f24a248-b328-43ec-8677-67600e42a8f7", "name": "Vance McDonald", "jersey": "89", "reference": "00-0030470", "position": "TE", "sr_id": "sr:player:831385", "penalties": 1, "yards": 10}, {"id": "f340201b-a1b1-43ba-a47a-484a44334553", "name": "T.J. Watt", "jersey": "90", "reference": "00-0033886", "position": "LB", "sr_id": "sr:player:1129547", "penalties": 1, "yards": 5}, {"id": "f7e3c1cb-6ec1-45fa-ad64-6b01957c34b1", "name": "David DeCastro", "jersey": "66", "reference": "00-0029678", "position": "G", "sr_id": "sr:player:827423", "penalties": 1, "yards": 5}, {"id": "244c00c7-fe9a-4f4f-adff-1d5b9c8877e7", "name": "Diontae Johnson", "jersey": "18", "reference": "00-0035216", "position": "WR", "sr_id": "sr:player:1221954", "penalties": 2, "yards": 15}, {"id": "6c2c4e4c-82f0-46e2-bcfb-3ed5f452266b", "name": "Maurkice Pouncey", "jersey": "53", "reference": "00-0027870", "position": "C", "sr_id": "sr:player:827723", "penalties": 2, "yards": 20}, {"id": "d088fb7a-694a-4286-a51d-4a13ec398088", "name": "Zach Banner", "jersey": "72", "reference": "00-0033785", "position": "T", "sr_id": "sr:player:1130195", "penalties": 1, "yards": 10}]}, "passing": {"totals": {"attempts": 36, "completions": 20, "cmp_pct": 55.6, "interceptions": 1, "sack_yards": 15, "rating": 84.4, "touchdowns": 2, "avg_yards": 6.2, "sacks": 2, "longest": 45, "longest_touchdown": 45, "air_yards": 151, "redzone_attempts": 3, "net_yards": 236, "yards": 251, "throw_aways": 1, "poor_throws": 7, "defended_passes": 7, "dropped_passes": 1, "spikes": 0, "blitzes": 22, "hurries": 2, "knockdowns": 5, "pocket_time": 110.29399999999998, "batted_passes": 1, "on_target_throws": 23}, "players": [{"id": "be4ca0ad-f3d6-4b98-a37f-79d0cbc06390", "name": "Mason Rudolph", "jersey": "02", "reference": "00-0034771", "position": "QB", "sr_id": "sr:player:1226430", "attempts": 36, "completions": 20, "cmp_pct": 55.6, "yards": 251, "avg_yards": 7.0, "sacks": 2, "sack_yards": 15, "touchdowns": 2, "longest": 45, "interceptions": 1, "rating": 84.4, "longest_touchdown": 45, "air_yards": 151, "redzone_attempts": 3, "throw_aways": 1, "poor_throws": 7, "defended_passes": 7, "dropped_passes": 1, "spikes": 0, "blitzes": 22, "hurries": 2, "knockdowns": 5, "pocket_time": 110.29399999999998, "avg_pocket_time": 3.064, "batted_passes": 1, "on_target_throws": 23}]}, "misc_returns": {"totals": {"yards": 0, "touchdowns": 0, "blk_fg_touchdowns": 0, "blk_punt_touchdowns": 0, "fg_return_touchdowns": 0, "ez_rec_touchdowns": 0, "number": 0}, "players": []}, "kickoffs": {"totals": {"endzone": 0, "inside_20": 0, "return_yards": 83, "touchbacks": 2, "yards": 363, "out_of_bounds": 0, "number": 6, "onside_attempts": 0, "onside_successes": 0, "squib_kicks": 0, "total_endzone": 2}, "players": [{"id": "441eb531-1ec8-4f65-9174-78bc6adada63", "name": "Chris Boswell", "jersey": "09", "reference": "00-0031136", "position": "K", "sr_id": "sr:player:829301", "endzone": 0, "inside_20": 0, "return_yards": 83, "touchbacks": 2, "yards": 363, "out_of_bounds": 0, "number": 6, "onside_attempts": 0, "onside_successes": 0, "squib_kicks": 0, "total_endzone": 2}]}, "kick_returns": {"totals": {"avg_yards": 25.0, "yards": 25, "longest": 25, "touchdowns": 0, "longest_touchdown": 0, "faircatches": 0, "number": 1}, "players": [{"id": "6259f62d-e16f-4369-a3be-ca02f79f3026", "name": "Ryan Switzer", "jersey": "10", "reference": "00-0033562", "position": "WR", "sr_id": "sr:player:1130155", "avg_yards": 25.0, "yards": 25, "longest": 25, "touchdowns": 0, "longest_touchdown": 0, "faircatches": 0, "number": 1}]}, "int_returns": {"totals": {"avg_yards": 3.0, "yards": 6, "longest": 6, "touchdowns": 0, "longest_touchdown": 0, "number": 2}, "players": [{"id": "1aede0b9-557c-444d-9a2f-4cc690e1563c", "name": "Minkah Fitzpatrick", "jersey": "39", "reference": "00-0034789", "position": "S", "sr_id": "sr:player:1473430", "avg_yards": 3.0, "yards": 6, "longest": 6, "touchdowns": 0, "longest_touchdown": 0, "number": 2}]}, "fumbles": {"totals": {"fumbles": 1, "lost_fumbles": 0, "own_rec": 1, "own_rec_yards": 0, "opp_rec": 2, "opp_rec_yards": 0, "out_of_bounds": 0, "forced_fumbles": 3, "own_rec_tds": 0, "opp_rec_tds": 0, "ez_rec_tds": 0}, "players": [{"id": "c2e80cfc-33a8-43f4-a61e-57048244e4f8", "name": "Steven Nelson", "jersey": "22", "reference": "00-0032150", "position": "CB", "sr_id": "sr:player:834645", "fumbles": 0, "lost_fumbles": 0, "own_rec": 0, "own_rec_yards": 0, "opp_rec": 1, "opp_rec_yards": 0, "out_of_bounds": 0, "forced_fumbles": 0, "own_rec_tds": 0, "opp_rec_tds": 0, "ez_rec_tds": 0}, {"id": "f340201b-a1b1-43ba-a47a-484a44334553", "name": "T.J. Watt", "jersey": "90", "reference": "00-0033886", "position": "LB", "sr_id": "sr:player:1129547", "fumbles": 0, "lost_fumbles": 0, "own_rec": 0, "own_rec_yards": 0, "opp_rec": 1, "opp_rec_yards": 0, "out_of_bounds": 0, "forced_fumbles": 2, "own_rec_tds": 0, "opp_rec_tds": 0, "ez_rec_tds": 0}, {"id": "be4ca0ad-f3d6-4b98-a37f-79d0cbc06390", "name": "Mason Rudolph", "jersey": "02", "reference": "00-0034771", "position": "QB", "sr_id": "sr:player:1226430", "fumbles": 1, "lost_fumbles": 0, "own_rec": 0, "own_rec_yards": 0, "opp_rec": 0, "opp_rec_yards": 0, "out_of_bounds": 0, "forced_fumbles": 0, "own_rec_tds": 0, "opp_rec_tds": 0, "ez_rec_tds": 0}, {"id": "f7e3c1cb-6ec1-45fa-ad64-6b01957c34b1", "name": "David DeCastro", "jersey": "66", "reference": "00-0029678", "position": "G", "sr_id": "sr:player:827423", "fumbles": 0, "lost_fumbles": 0, "own_rec": 1, "own_rec_yards": 0, "opp_rec": 0, "opp_rec_yards": 0, "out_of_bounds": 0, "forced_fumbles": 0, "own_rec_tds": 0, "opp_rec_tds": 0, "ez_rec_tds": 0}, {"id": "972f93d7-158b-4464-b119-952f298cea52", "name": "Mike Hilton", "jersey": "28", "reference": "00-0032521", "position": "CB", "sr_id": "sr:player:989265", "fumbles": 0, "lost_fumbles": 0, "own_rec": 0, "own_rec_yards": 0, "opp_rec": 0, "opp_rec_yards": 0, "out_of_bounds": 0, "forced_fumbles": 1, "own_rec_tds": 0, "opp_rec_tds": 0, "ez_rec_tds": 0}]}, "field_goals": {"totals": {"attempts": 3, "made": 2, "blocked": 0, "yards": 83, "avg_yards": 27.667, "longest": 42, "net_attempts": 3}, "players": [{"id": "441eb531-1ec8-4f65-9174-78bc6adada63", "name": "Chris Boswell", "jersey": "09", "reference": "00-0031136", "position": "K", "sr_id": "sr:player:829301", "attempts": 3, "made": 2, "blocked": 0, "yards": 83, "avg_yards": 27.7, "longest": 42}]}, "extra_points": {"kicks": {"totals": {"attempts": 3, "blocked": 0, "made": 3}, "players": [{"id": "441eb531-1ec8-4f65-9174-78bc6adada63", "name": "Chris Boswell", "jersey": "09", "reference": "00-0031136", "position": "K", "sr_id": "sr:player:829301", "attempts": 3, "blocked": 0, "made": 3}]}, "conversions": {"totals": {"pass_attempts": 0, "pass_successes": 0, "rush_attempts": 0, "rush_successes": 0, "defense_attempts": 0, "defense_successes": 0, "turnover_successes": 0}, "players": []}}, "defense": {"totals": {"tackles": 36, "assists": 13, "combined": 49, "sacks": 4.0, "sack_yards": 20.0, "interceptions": 2, "passes_defended": 4, "forced_fumbles": 3, "fumble_recoveries": 2, "qb_hits": 10, "tloss": 2.0, "tloss_yards": 8.0, "safeties": 0, "sp_tackles": 7, "sp_assists": 0, "sp_forced_fumbles": 0, "sp_fumble_recoveries": 0, "sp_blocks": 0, "misc_tackles": 1, "misc_assists": 0, "misc_forced_fumbles": 0, "misc_fumble_recoveries": 1, "def_targets": 31, "def_comps": 20, "blitzes": 14, "hurries": 7, "knockdowns": 6, "missed_tackles": 5, "batted_passes": 0}, "players": [{"id": "3f8e4972-2361-4939-b5e3-c5f6c63b9f68", "name": "Javon Hargrave", "jersey": "79", "reference": "00-0033109", "position": "NT", "sr_id": "sr:player:1074106", "tackles": 1, "assists": 0, "combined": 1, "sacks": 0.0, "sack_yards": 0.0, "interceptions": 0, "passes_defended": 0, "forced_fumbles": 0, "fumble_recoveries": 0, "qb_hits": 0, "tloss": 0.0, "tloss_yards": 0.0, "safeties": 0, "sp_tackles": 0, "sp_assists": 0, "sp_forced_fumbles": 0, "sp_fumble_recoveries": 0, "sp_blocks": 0, "misc_tackles": 0, "misc_assists": 0, "misc_forced_fumbles": 0, "misc_fumble_recoveries": 0, "def_targets": 0, "def_comps": 0, "blitzes": 0, "hurries": 1, "knockdowns": 0, "missed_tackles": 0, "batted_passes": 0}, {"id": "0adb6bc1-17fd-4ca5-90ad-89ca06950bc8", "name": "Vince Williams", "jersey": "98", "reference": "00-0030434", "position": "LB", "sr_id": "sr:player:831349", "tackles": 3, "assists": 1, "combined": 4, "sacks": 0.0, "sack_yards": 0.0, "interceptions": 0, "passes_defended": 0, "forced_fumbles": 0, "fumble_recoveries": 0, "qb_hits": 2, "tloss": 0.0, "tloss_yards": 0.0, "safeties": 0, "sp_tackles": 0, "sp_assists": 0, "sp_forced_fumbles": 0, "sp_fumble_recoveries": 0, "sp_blocks": 0, "misc_tackles": 0, "misc_assists": 0, "misc_forced_fumbles": 0, "misc_fumble_recoveries": 0, "def_targets": 2, "def_comps": 2, "blitzes": 6, "hurries": 0, "knockdowns": 2, "missed_tackles": 0, "batted_passes": 0}, {"id": "ab5d4d72-fb1c-4aeb-887b-f6ca35f679bf", "name": "Devin Bush Jr.", "jersey": "55", "reference": "00-0035525", "position": "LB", "sr_id": "sr:player:1734409", "tackles": 6, "assists": 1, "combined": 7, "sacks": 0.0, "sack_yards": 0.0, "interceptions": 0, "passes_defended": 0, "forced_fumbles": 0, "fumble_recoveries": 0, "qb_hits": 0, "tloss": 0.0, "tloss_yards": 0.0, "safeties": 0, "sp_tackles": 0, "sp_assists": 0, "sp_forced_fumbles": 0, "sp_fumble_recoveries": 0, "sp_blocks": 0, "misc_tackles": 0, "misc_assists": 0, "misc_forced_fumbles": 0, "misc_fumble_recoveries": 0, "def_targets": 4, "def_comps": 4, "blitzes": 2, "hurries": 0, "knockdowns": 0, "missed_tackles": 1, "batted_passes": 0}, {"id": "f340201b-a1b1-43ba-a47a-484a44334553", "name": "T.J. Watt", "jersey": "90", "reference": "00-0033886", "position": "LB", "sr_id": "sr:player:1129547", "tackles": 3, "assists": 0, "combined": 3, "sacks": 2.0, "sack_yards": 16.0, "interceptions": 0, "passes_defended": 0, "forced_fumbles": 2, "fumble_recoveries": 1, "qb_hits": 3, "tloss": 0.0, "tloss_yards": 0.0, "safeties": 0, "sp_tackles": 0, "sp_assists": 0, "sp_forced_fumbles": 0, "sp_fumble_recoveries": 0, "sp_blocks": 0, "misc_tackles": 0, "misc_assists": 0, "misc_forced_fumbles": 0, "misc_fumble_recoveries": 0, "def_targets": 0, "def_comps": 0, "blitzes": 1, "hurries": 3, "knockdowns": 1, "missed_tackles": 0, "batted_passes": 0}, {"id": "98c7ad4f-8e63-4028-b3ca-84dd37a5ae64", "name": "Mark Barron", "jersey": "26", "reference": "00-0029670", "position": "LB", "sr_id": "sr:player:829855", "tackles": 3, "assists": 2, "combined": 5, "sacks": 0.0, "sack_yards": 0.0, "interceptions": 0, "passes_defended": 0, "forced_fumbles": 0, "fumble_recoveries": 0, "qb_hits": 0, "tloss": 0.0, "tloss_yards": 0.0, "safeties": 0, "sp_tackles": 0, "sp_assists": 0, "sp_forced_fumbles": 0, "sp_fumble_recoveries": 0, "sp_blocks": 0, "misc_tackles": 0, "misc_assists": 0, "misc_forced_fumbles": 0, "misc_fumble_recoveries": 0, "def_targets": 4, "def_comps": 3, "blitzes": 0, "hurries": 0, "knockdowns": 0, "missed_tackles": 2, "batted_passes": 0}, {"id": "9b4e4d1d-ad88-4c10-b1c0-b9116755c184", "name": "Trey Edmunds", "jersey": "33", "reference": "00-0033838", "position": "TE", "sr_id": "sr:player:1135277", "tackles": 0, "assists": 0, "combined": 0, "sacks": 0.0, "sack_yards": 0.0, "interceptions": 0, "passes_defended": 0, "forced_fumbles": 0, "fumble_recoveries": 0, "qb_hits": 0, "tloss": 0.0, "tloss_yards": 0.0, "safeties": 0, "sp_tackles": 2, "sp_assists": 0, "sp_forced_fumbles": 0, "sp_fumble_recoveries": 0, "sp_blocks": 0, "misc_tackles": 0, "misc_assists": 0, "misc_forced_fumbles": 0, "misc_fumble_recoveries": 0, "def_targets": 0, "def_comps": 0, "blitzes": 0, "hurries": 0, "knockdowns": 0, "missed_tackles": 0, "batted_passes": 0}, {"id": "784b55b7-2822-4f38-9daa-a704151d1b35", "name": "Jordan Dangerfield", "jersey": "37", "reference": "00-0030023", "position": "S", "sr_id": "sr:player:830471", "tackles": 0, "assists": 0, "combined": 0, "sacks": 0.0, "sack_yards": 0.0, "interceptions": 0, "passes_defended": 0, "forced_fumbles": 0, "fumble_recoveries": 0, "qb_hits": 0, "tloss": 0.0, "tloss_yards": 0.0, "safeties": 0, "sp_tackles": 1, "sp_assists": 0, "sp_forced_fumbles": 0, "sp_fumble_recoveries": 0, "sp_blocks": 0, "misc_tackles": 0, "misc_assists": 0, "misc_forced_fumbles": 0, "misc_fumble_recoveries": 0, "def_targets": 0, "def_comps": 0, "blitzes": 0, "hurries": 0, "knockdowns": 0, "missed_tackles": 0, "batted_passes": 0}, {"id": "1aede0b9-557c-444d-9a2f-4cc690e1563c", "name": "Minkah Fitzpatrick", "jersey": "39", "reference": "00-0034789", "position": "S", "sr_id": "sr:player:1473430", "tackles": 1, "assists": 1, "combined": 2, "sacks": 0.0, "sack_yards": 0.0, "interceptions": 2, "passes_defended": 2, "forced_fumbles": 0, "fumble_recoveries": 0, "qb_hits": 0, "tloss": 0.0, "tloss_yards": 0.0, "safeties": 0, "sp_tackles": 0, "sp_assists": 0, "sp_forced_fumbles": 0, "sp_fumble_recoveries": 0, "sp_blocks": 0, "misc_tackles": 0, "misc_assists": 0, "misc_forced_fumbles": 0, "misc_fumble_recoveries": 0, "def_targets": 2, "def_comps": 0, "blitzes": 0, "hurries": 0, "knockdowns": 0, "missed_tackles": 0, "batted_passes": 0}, {"id": "c2e80cfc-33a8-43f4-a61e-57048244e4f8", "name": "Steven Nelson", "jersey": "22", "reference": "00-0032150", "position": "CB", "sr_id": "sr:player:834645", "tackles": 1, "assists": 0, "combined": 1, "sacks": 0.0, "sack_yards": 0.0, "interceptions": 0, "passes_defended": 0, "forced_fumbles": 0, "fumble_recoveries": 1, "qb_hits": 0, "tloss": 0.0, "tloss_yards": 0.0, "safeties": 0, "sp_tackles": 0, "sp_assists": 0, "sp_forced_fumbles": 0, "sp_fumble_recoveries": 0, "sp_blocks": 0, "misc_tackles": 0, "misc_assists": 0, "misc_forced_fumbles": 0, "misc_fumble_recoveries": 0, "def_targets": 7, "def_comps": 3, "blitzes": 0, "hurries": 0, "knockdowns": 0, "missed_tackles": 0, "batted_passes": 0}, {"id": "3ec2ad5e-f4e0-474a-98a9-0bde4ff5aab9", "name": "Joe Haden", "jersey": "23", "reference": "00-0027860", "position": "CB", "sr_id": "sr:player:829149", "tackles": 7, "assists": 1, "combined": 8, "sacks": 0.0, "sack_yards": 0.0, "interceptions": 0, "passes_defended": 0, "forced_fumbles": 0, "fumble_recoveries": 0, "qb_hits": 0, "tloss": 0.0, "tloss_yards": 0.0, "safeties": 0, "sp_tackles": 0, "sp_assists": 0, "sp_forced_fumbles": 0, "sp_fumble_recoveries": 0, "sp_blocks": 0, "misc_tackles": 0, "misc_assists": 0, "misc_forced_fumbles": 0, "misc_fumble_recoveries": 0, "def_targets": 6, "def_comps": 5, "blitzes": 0, "hurries": 0, "knockdowns": 0, "missed_tackles": 0, "batted_passes": 0}, {"id": "9547fbb1-0d4f-4d9e-83b9-e2fa30463bb9", "name": "JuJu Smith-Schuster", "jersey": "19", "reference": "00-0033857", "position": "WR", "sr_id": "sr:player:1129761", "tackles": 0, "assists": 0, "combined": 0, "sacks": 0.0, "sack_yards": 0.0, "interceptions": 0, "passes_defended": 0, "forced_fumbles": 0, "fumble_recoveries": 0, "qb_hits": 0, "tloss": 0.0, "tloss_yards": 0.0, "safeties": 0, "sp_tackles": 0, "sp_assists": 0, "sp_forced_fumbles": 0, "sp_fumble_recoveries": 0, "sp_blocks": 0, "misc_tackles": 1, "misc_assists": 0, "misc_forced_fumbles": 0, "misc_fumble_recoveries": 0, "def_targets": 0, "def_comps": 0, "blitzes": 0, "hurries": 0, "knockdowns": 0, "missed_tackles": 0, "batted_passes": 0}, {"id": "4642915e-8c37-4692-9169-fa210b6efc8c", "name": "Jayrone Elliott", "jersey": "51", "reference": "00-0030752", "position": "LB", "sr_id": "sr:player:831503", "tackles": 0, "assists": 0, "combined": 0, "sacks": 0.0, "sack_yards": 0.0, "interceptions": 0, "passes_defended": 0, "forced_fumbles": 0, "fumble_recoveries": 0, "qb_hits": 0, "tloss": 0.0, "tloss_yards": 0.0, "safeties": 0, "sp_tackles": 1, "sp_assists": 0, "sp_forced_fumbles": 0, "sp_fumble_recoveries": 0, "sp_blocks": 0, "misc_tackles": 0, "misc_assists": 0, "misc_forced_fumbles": 0, "misc_fumble_recoveries": 0, "def_targets": 0, "def_comps": 0, "blitzes": 1, "hurries": 0, "knockdowns": 0, "missed_tackles": 0, "batted_passes": 0}, {"id": "1aa8d83f-c084-4893-b9b0-b1296ec822f1", "name": "Tyson Alualu", "jersey": "94", "reference": "00-0027862", "position": "DE", "sr_id": "sr:player:830745", "tackles": 1, "assists": 1, "combined": 2, "sacks": 0.0, "sack_yards": 0.0, "interceptions": 0, "passes_defended": 0, "forced_fumbles": 0, "fumble_recoveries": 0, "qb_hits": 1, "tloss": 0.0, "tloss_yards": 0.0, "safeties": 0, "sp_tackles": 0, "sp_assists": 0, "sp_forced_fumbles": 0, "sp_fumble_recoveries": 0, "sp_blocks": 0, "misc_tackles": 0, "misc_assists": 0, "misc_forced_fumbles": 0, "misc_fumble_recoveries": 0, "def_targets": 0, "def_comps": 0, "blitzes": 0, "hurries": 2, "knockdowns": 1, "missed_tackles": 0, "batted_passes": 0}, {"id": "9779acc7-ed88-4a16-b78d-230ace9ec3eb", "name": "Cameron Heyward", "jersey": "97", "reference": "00-0027969", "position": "DT", "sr_id": "sr:player:829603", "tackles": 3, "assists": 3, "combined": 6, "sacks": 1.0, "sack_yards": 4.0, "interceptions": 0, "passes_defended": 1, "forced_fumbles": 0, "fumble_recoveries": 0, "qb_hits": 2, "tloss": 1.0, "tloss_yards": 4.0, "safeties": 0, "sp_tackles": 0, "sp_assists": 0, "sp_forced_fumbles": 0, "sp_fumble_recoveries": 0, "sp_blocks": 0, "misc_tackles": 0, "misc_assists": 0, "misc_forced_fumbles": 0, "misc_fumble_recoveries": 0, "def_targets": 1, "def_comps": 0, "blitzes": 0, "hurries": 0, "knockdowns": 1, "missed_tackles": 0, "batted_passes": 0}, {"id": "f7e3c1cb-6ec1-45fa-ad64-6b01957c34b1", "name": "David DeCastro", "jersey": "66", "reference": "00-0029678", "position": "G", "sr_id": "sr:player:827423", "tackles": 0, "assists": 0, "combined": 0, "sacks": 0.0, "sack_yards": 0.0, "interceptions": 0, "passes_defended": 0, "forced_fumbles": 0, "fumble_recoveries": 0, "qb_hits": 0, "tloss": 0.0, "tloss_yards": 0.0, "safeties": 0, "sp_tackles": 0, "sp_assists": 0, "sp_forced_fumbles": 0, "sp_fumble_recoveries": 0, "sp_blocks": 0, "misc_tackles": 0, "misc_assists": 0, "misc_forced_fumbles": 0, "misc_fumble_recoveries": 1, "def_targets": 0, "def_comps": 0, "blitzes": 0, "hurries": 0, "knockdowns": 0, "missed_tackles": 0, "batted_passes": 0}, {"id": "74af3906-083e-49d1-b8c6-556101390381", "name": "Benny Snell Jr.", "jersey": "24", "reference": "00-0035217", "position": "RB", "sr_id": "sr:player:1734857", "tackles": 0, "assists": 0, "combined": 0, "sacks": 0.0, "sack_yards": 0.0, "interceptions": 0, "passes_defended": 0, "forced_fumbles": 0, "fumble_recoveries": 0, "qb_hits": 0, "tloss": 0.0, "tloss_yards": 0.0, "safeties": 0, "sp_tackles": 1, "sp_assists": 0, "sp_forced_fumbles": 0, "sp_fumble_recoveries": 0, "sp_blocks": 0, "misc_tackles": 0, "misc_assists": 0, "misc_forced_fumbles": 0, "misc_fumble_recoveries": 0, "def_targets": 0, "def_comps": 0, "blitzes": 0, "hurries": 0, "knockdowns": 0, "missed_tackles": 0, "batted_passes": 0}, {"id": "e4739abd-d524-4857-85fc-ed4845462817", "name": "Terrell Edmunds", "jersey": "34", "reference": "00-0034858", "position": "S", "sr_id": "sr:player:1473440", "tackles": 3, "assists": 1, "combined": 4, "sacks": 0.0, "sack_yards": 0.0, "interceptions": 0, "passes_defended": 0, "forced_fumbles": 0, "fumble_recoveries": 0, "qb_hits": 0, "tloss": 0.0, "tloss_yards": 0.0, "safeties": 0, "sp_tackles": 0, "sp_assists": 0, "sp_forced_fumbles": 0, "sp_fumble_recoveries": 0, "sp_blocks": 0, "misc_tackles": 0, "misc_assists": 0, "misc_forced_fumbles": 0, "misc_fumble_recoveries": 0, "def_targets": 3, "def_comps": 2, "blitzes": 0, "hurries": 0, "knockdowns": 0, "missed_tackles": 0, "batted_passes": 0}, {"id": "b217c699-2eb4-4c60-9d7f-2df8e4232009", "name": "Tyler Matakevich", "jersey": "44", "reference": "00-0032366", "position": "LB", "sr_id": "sr:player:988613", "tackles": 0, "assists": 0, "combined": 0, "sacks": 0.0, "sack_yards": 0.0, "interceptions": 0, "passes_defended": 0, "forced_fumbles": 0, "fumble_recoveries": 0, "qb_hits": 0, "tloss": 0.0, "tloss_yards": 0.0, "safeties": 0, "sp_tackles": 2, "sp_assists": 0, "sp_forced_fumbles": 0, "sp_fumble_recoveries": 0, "sp_blocks": 0, "misc_tackles": 0, "misc_assists": 0, "misc_forced_fumbles": 0, "misc_fumble_recoveries": 0, "def_targets": 0, "def_comps": 0, "blitzes": 0, "hurries": 0, "knockdowns": 0, "missed_tackles": 0, "batted_passes": 0}, {"id": "972f93d7-158b-4464-b119-952f298cea52", "name": "Mike Hilton", "jersey": "28", "reference": "00-0032521", "position": "CB", "sr_id": "sr:player:989265", "tackles": 1, "assists": 0, "combined": 1, "sacks": 0.0, "sack_yards": 0.0, "interceptions": 0, "passes_defended": 1, "forced_fumbles": 1, "fumble_recoveries": 0, "qb_hits": 1, "tloss": 0.0, "tloss_yards": 0.0, "safeties": 0, "sp_tackles": 0, "sp_assists": 0, "sp_forced_fumbles": 0, "sp_fumble_recoveries": 0, "sp_blocks": 0, "misc_tackles": 0, "misc_assists": 0, "misc_forced_fumbles": 0, "misc_fumble_recoveries": 0, "def_targets": 1, "def_comps": 0, "blitzes": 4, "hurries": 0, "knockdowns": 1, "missed_tackles": 0, "batted_passes": 0}, {"id": "48dca4c3-c6ac-4122-aee6-26f7cd259824", "name": "Bud Dupree", "jersey": "48", "reference": "00-0032146", "position": "LB", "sr_id": "sr:player:834527", "tackles": 3, "assists": 2, "combined": 5, "sacks": 1.0, "sack_yards": 0.0, "interceptions": 0, "passes_defended": 0, "forced_fumbles": 0, "fumble_recoveries": 0, "qb_hits": 1, "tloss": 1.0, "tloss_yards": 4.0, "safeties": 0, "sp_tackles": 0, "sp_assists": 0, "sp_forced_fumbles": 0, "sp_fumble_recoveries": 0, "sp_blocks": 0, "misc_tackles": 0, "misc_assists": 0, "misc_forced_fumbles": 0, "misc_fumble_recoveries": 0, "def_targets": 1, "def_comps": 1, "blitzes": 0, "hurries": 1, "knockdowns": 0, "missed_tackles": 2, "batted_passes": 0}]}, "efficiency": {"goaltogo": {"attempts": 0, "successes": 0, "pct": 0.0}, "redzone": {"attempts": 2, "successes": 1, "pct": 50.0}, "thirddown": {"attempts": 13, "successes": 6, "pct": 46.154}, "fourthdown": {"attempts": 1, "successes": 0, "pct": 0.0}}, "first_downs": {"pass": 12, "penalty": 2, "rush": 7, "total": 21}, "interceptions": {"return_yards": 6, "returned": 2, "number": 2}, "touchdowns": {"pass": 2, "rush": 1, "total_return": 0, "total": 3, "fumble_return": 0, "int_return": 0, "kick_return": 0, "punt_return": 0, "other": 0}}, "away": {"id": "4809ecb0-abd3-451d-9c4a-92a90b83ca06", "name": "Dolphins", "market": "Miami", "alias": "MIA", "reference": "5094", "sr_id": "sr:competitor:4287", "summary": {"possession_time": "24:42", "avg_gain": 4.0, "safeties": 0, "turnovers": 4, "play_count": 57, "rush_plays": 19, "total_yards": 230, "fumbles": 3, "lost_fumbles": 2, "penalties": 5, "penalty_yards": 45, "return_yards": 35}, "rushing": {"totals": {"avg_yards": 3.2, "attempts": 19, "touchdowns": 0, "tlost": 1, "tlost_yards": -4, "yards": 60, "longest": 9, "longest_touchdown": 0, "redzone_attempts": 2, "broken_tackles": 0, "kneel_downs": 1, "scrambles": 3, "yards_after_contact": 18}, "players": [{"id": "c6728282-0648-4926-a07c-be64f3ff5e0d", "name": "Kalen Ballage", "jersey": "27", "reference": "00-0034799", "position": "RB", "sr_id": "sr:player:1475118", "avg_yards": 2.7, "attempts": 3, "touchdowns": 0, "yards": 8, "longest": 4, "longest_touchdown": 0, "redzone_attempts": 1, "tlost": 0, "tlost_yards": 0, "broken_tackles": 0, "kneel_downs": 0, "scrambles": 0, "yards_after_contact": 2}, {"id": "0742d2ea-1cf2-49a6-a150-77ba6e034d8c", "name": "Ryan Fitzpatrick", "jersey": "14", "reference": "00-0023682", "position": "QB", "sr_id": "sr:player:831033", "avg_yards": 3.4, "attempts": 5, "touchdowns": 0, "yards": 17, "longest": 8, "longest_touchdown": 0, "redzone_attempts": 0, "tlost": 0, "tlost_yards": 0, "broken_tackles": 0, "kneel_downs": 1, "scrambles": 3, "yards_after_contact": 6}, {"id": "b120cb2d-04b8-4dd3-809e-92c9b4c29b0c", "name": "Mark Walton", "jersey": "22", "reference": "00-0034679", "position": "RB", "sr_id": "sr:player:1474712", "avg_yards": 3.2, "attempts": 11, "touchdowns": 0, "yards": 35, "longest": 9, "longest_touchdown": 0, "redzone_attempts": 1, "tlost": 1, "tlost_yards": -4, "broken_tackles": 0, "kneel_downs": 0, "scrambles": 0, "yards_after_contact": 10}]}, "receiving": {"totals": {"targets": 33, "receptions": 21, "avg_yards": 9.048, "yards": 190, "touchdowns": 2, "yards_after_catch": 61, "longest": 17, "longest_touchdown": 12, "redzone_targets": 2, "air_yards": 129, "broken_tackles": 1, "dropped_passes": 3, "catchable_passes": 3, "yards_after_contact": 13}, "players": [{"id": "1012cbe0-7eba-4169-bfca-183a0204e1a7", "name": "Mike Gesicki", "jersey": "88", "reference": "00-0034829", "position": "TE", "sr_id": "sr:player:1218868", "receptions": 2, "targets": 3, "yards": 10, "avg_yards": 5.0, "longest": 5, "touchdowns": 0, "longest_touchdown": 0, "yards_after_catch": 4, "redzone_targets": 0, "air_yards": 6, "broken_tackles": 0, "dropped_passes": 0, "catchable_passes": 0, "yards_after_contact": 0}, {"id": "e9ee9209-dd8f-4e4a-be3c-407756a2749c", "name": "DeVante Parker", "jersey": "11", "reference": "00-0031547", "position": "WR", "sr_id": "sr:player:834525", "receptions": 6, "targets": 8, "yards": 59, "avg_yards": 9.8, "longest": 15, "touchdowns": 0, "longest_touchdown": 0, "yards_after_catch": 10, "redzone_targets": 0, "air_yards": 49, "broken_tackles": 0, "dropped_passes": 0, "catchable_passes": 0, "yards_after_contact": 3}, {"id": "2958ea86-e2dc-4719-93e5-cc9d093ca963", "name": "Albert Wilson", "jersey": "15", "reference": "00-0030669", "position": "WR", "sr_id": "sr:player:828339", "receptions": 1, "targets": 2, "yards": 5, "avg_yards": 5.0, "longest": 5, "touchdowns": 1, "longest_touchdown": 5, "yards_after_catch": 3, "redzone_targets": 1, "air_yards": 2, "broken_tackles": 0, "dropped_passes": 0, "catchable_passes": 0, "yards_after_contact": 0}, {"id": "c6728282-0648-4926-a07c-be64f3ff5e0d", "name": "Kalen Ballage", "jersey": "27", "reference": "00-0034799", "position": "RB", "sr_id": "sr:player:1475118", "receptions": 1, "targets": 1, "yards": 11, "avg_yards": 11.0, "longest": 11, "touchdowns": 0, "longest_touchdown": 0, "yards_after_catch": 14, "redzone_targets": 0, "air_yards": -3, "broken_tackles": 0, "dropped_passes": 0, "catchable_passes": 0, "yards_after_contact": 0}, {"id": "6d96bf47-e8c7-4683-8291-74dc426a38cb", "name": "Michael Deiter", "jersey": "63", "reference": "00-0035686", "position": "G", "sr_id": "sr:player:1853496", "receptions": 1, "targets": 1, "yards": 0, "avg_yards": 0.0, "longest": 0, "touchdowns": 0, "longest_touchdown": 0, "yards_after_catch": 0, "redzone_targets": 0, "air_yards": 0, "broken_tackles": 0, "dropped_passes": 0, "catchable_passes": 0, "yards_after_contact": 0}, {"id": "5de11f0b-8da9-42ba-9a93-db7f0a58543b", "name": "Jakeem Grant", "jersey": "19", "reference": "00-0032791", "position": "WR", "sr_id": "sr:player:988619", "receptions": 2, "targets": 3, "yards": 32, "avg_yards": 16.0, "longest": 17, "touchdowns": 0, "longest_touchdown": 0, "yards_after_catch": 1, "redzone_targets": 0, "air_yards": 31, "broken_tackles": 0, "dropped_passes": 0, "catchable_passes": 0, "yards_after_contact": 0}, {"id": "c257b2e6-dfc9-45c8-b30c-a497f2ce82a2", "name": "Nick O'Leary", "jersey": "83", "reference": "00-0032117", "position": "TE", "sr_id": "sr:player:835195", "receptions": 0, "targets": 1, "yards": 0, "avg_yards": 0.0, "longest": 0, "touchdowns": 0, "longest_touchdown": 0, "yards_after_catch": 0, "redzone_targets": 0, "air_yards": 0, "broken_tackles": 0, "dropped_passes": 1, "catchable_passes": 1, "yards_after_contact": 0}, {"id": "b120cb2d-04b8-4dd3-809e-92c9b4c29b0c", "name": "Mark Walton", "jersey": "22", "reference": "00-0034679", "position": "RB", "sr_id": "sr:player:1474712", "receptions": 3, "targets": 6, "yards": 19, "avg_yards": 6.3, "longest": 9, "touchdowns": 0, "longest_touchdown": 0, "yards_after_catch": 17, "redzone_targets": 0, "air_yards": 2, "broken_tackles": 0, "dropped_passes": 1, "catchable_passes": 1, "yards_after_contact": 3}, {"id": "497758de-5f0b-481f-8c68-7aa5e21df322", "name": "Preston Williams", "jersey": "18", "reference": "00-0035350", "position": "WR", "sr_id": "sr:player:1216724", "receptions": 4, "targets": 7, "yards": 42, "avg_yards": 10.5, "longest": 14, "touchdowns": 0, "longest_touchdown": 0, "yards_after_catch": 6, "redzone_targets": 0, "air_yards": 36, "broken_tackles": 0, "dropped_passes": 1, "catchable_passes": 1, "yards_after_contact": 0}, {"id": "10952a8e-9da1-447b-a016-c699db00c5f0", "name": "Allen Hurns", "jersey": "17", "reference": "00-0030821", "position": "WR", "sr_id": "sr:player:855802", "receptions": 1, "targets": 1, "yards": 12, "avg_yards": 12.0, "longest": 12, "touchdowns": 1, "longest_touchdown": 12, "yards_after_catch": 6, "redzone_targets": 1, "air_yards": 6, "broken_tackles": 1, "dropped_passes": 0, "catchable_passes": 0, "yards_after_contact": 7}]}, "punts": {"totals": {"attempts": 2, "yards": 93, "net_yards": 91, "blocked": 0, "touchbacks": 0, "inside_20": 2, "return_yards": 2, "avg_net_yards": 45.5, "avg_yards": 46.5, "longest": 58, "hang_time": 8.8, "avg_hang_time": 4.4}, "players": [{"id": "9164fac3-2540-4f64-ba29-96fb0ce1c7eb", "name": "Matt Haack", "jersey": "02", "reference": "00-0033400", "position": "P", "sr_id": "sr:player:1133765", "attempts": 2, "yards": 93, "avg_yards": 46.5, "blocked": 0, "longest": 58, "touchbacks": 0, "inside_20": 2, "avg_net_yards": 45.5, "return_yards": 2, "net_yards": 91, "hang_time": 8.8, "avg_hang_time": 4.4}]}, "punt_returns": {"totals": {"avg_yards": 11.667, "yards": 35, "longest": 19, "touchdowns": 0, "longest_touchdown": 0, "faircatches": 0, "number": 3}, "players": [{"id": "497758de-5f0b-481f-8c68-7aa5e21df322", "name": "Preston Williams", "jersey": "18", "reference": "00-0035350", "position": "WR", "sr_id": "sr:player:1216724", "yards": 35, "avg_yards": 11.7, "touchdowns": 0, "longest": 19, "faircatches": 0, "longest_touchdown": 0, "number": 3}]}, "penalties": {"totals": {"penalties": 5, "yards": 45}, "players": [{"id": "d4b7a6b6-9ad3-4bc9-b781-dc09e9a5ba01", "name": "Jesse Davis", "jersey": "77", "reference": "00-0031893", "position": "G/T", "sr_id": "sr:player:836247", "penalties": 1, "yards": 5}, {"id": "a57a96ca-7aa8-4e0f-9ba8-437690fe50dc", "name": "Deon Lacey", "jersey": "44", "reference": "00-0030197", "position": "LB", "sr_id": "sr:player:1091978", "penalties": 1, "yards": 5}, {"id": "03e6a751-5206-4f9e-8ffa-f92672f7c159", "name": "Nik Needham", "jersey": "40", "reference": "00-0035346", "position": "DB", "sr_id": "sr:player:1182112", "penalties": 1, "yards": 5}, {"id": "5dd5a4bf-08f1-46e1-bf31-eab422cef869", "name": "Evan Boehm", "jersey": "76", "reference": "00-0032777", "position": "C/G", "sr_id": "sr:player:1074056", "penalties": 1, "yards": 5}, {"id": "ba95b150-fad0-4a8d-b15d-a5e318d95b7f", "name": "Ryan Lewis", "jersey": "24", "reference": "00-0033608", "position": "CB", "sr_id": "sr:player:1131359", "penalties": 1, "yards": 25}]}, "passing": {"totals": {"attempts": 34, "completions": 21, "cmp_pct": 61.8, "interceptions": 2, "sack_yards": 20, "rating": 71.9, "touchdowns": 2, "avg_yards": 4.5, "sacks": 4, "longest": 17, "longest_touchdown": 12, "air_yards": 129, "redzone_attempts": 2, "net_yards": 170, "yards": 190, "throw_aways": 1, "poor_throws": 7, "defended_passes": 2, "dropped_passes": 3, "spikes": 0, "blitzes": 14, "hurries": 6, "knockdowns": 6, "pocket_time": 94.024, "batted_passes": 0, "on_target_throws": 23}, "players": [{"id": "0742d2ea-1cf2-49a6-a150-77ba6e034d8c", "name": "Ryan Fitzpatrick", "jersey": "14", "reference": "00-0023682", "position": "QB", "sr_id": "sr:player:831033", "attempts": 34, "completions": 21, "cmp_pct": 61.8, "yards": 190, "avg_yards": 5.6, "sacks": 4, "sack_yards": 20, "touchdowns": 2, "longest": 17, "interceptions": 2, "rating": 71.9, "longest_touchdown": 12, "air_yards": 129, "redzone_attempts": 2, "throw_aways": 1, "poor_throws": 7, "defended_passes": 2, "dropped_passes": 3, "spikes": 0, "blitzes": 14, "hurries": 6, "knockdowns": 6, "pocket_time": 94.024, "avg_pocket_time": 2.765, "batted_passes": 0, "on_target_throws": 23}]}, "misc_returns": {"totals": {"yards": 0, "touchdowns": 0, "blk_fg_touchdowns": 0, "blk_punt_touchdowns": 0, "fg_return_touchdowns": 0, "ez_rec_touchdowns": 0, "number": 0}, "players": []}, "kickoffs": {"totals": {"endzone": 1, "inside_20": 0, "return_yards": 25, "touchbacks": 2, "yards": 196, "out_of_bounds": 0, "number": 3, "onside_attempts": 0, "onside_successes": 0, "squib_kicks": 0, "total_endzone": 3}, "players": [{"id": "5ffb654f-0de5-424b-aa2f-ad511deb5b51", "name": "Jason Sanders", "jersey": "07", "reference": "00-0034794", "position": "K", "sr_id": "sr:player:1475108", "endzone": 1, "inside_20": 0, "return_yards": 25, "touchbacks": 2, "yards": 196, "out_of_bounds": 0, "number": 3, "onside_attempts": 0, "onside_successes": 0, "squib_kicks": 0, "total_endzone": 3}]}, "kick_returns": {"totals": {"avg_yards": 20.75, "yards": 83, "longest": 24, "touchdowns": 0, "longest_touchdown": 0, "faircatches": 0, "number": 4}, "players": [{"id": "5de11f0b-8da9-42ba-9a93-db7f0a58543b", "name": "Jakeem Grant", "jersey": "19", "reference": "00-0032791", "position": "WR", "sr_id": "sr:player:988619", "avg_yards": 20.8, "yards": 83, "longest": 24, "touchdowns": 0, "longest_touchdown": 0, "faircatches": 0, "number": 4}]}, "int_returns": {"totals": {"avg_yards": 0.0, "yards": 0, "longest": 0, "touchdowns": 0, "longest_touchdown": 0, "number": 1}, "players": [{"id": "e6bcb4f1-c2c8-4dd9-b826-af01182875f2", "name": "Xavien Howard", "jersey": "25", "reference": "00-0033050", "position": "CB", "sr_id": "sr:player:987645", "avg_yards": 0.0, "yards": 0, "longest": 0, "touchdowns": 0, "longest_touchdown": 0, "number": 1}]}, "fumbles": {"totals": {"fumbles": 3, "lost_fumbles": 2, "own_rec": 1, "own_rec_yards": 0, "opp_rec": 0, "opp_rec_yards": 0, "out_of_bounds": 0, "forced_fumbles": 1, "own_rec_tds": 0, "opp_rec_tds": 0, "ez_rec_tds": 0}, "players": [{"id": "b120cb2d-04b8-4dd3-809e-92c9b4c29b0c", "name": "Mark Walton", "jersey": "22", "reference": "00-0034679", "position": "RB", "sr_id": "sr:player:1474712", "fumbles": 1, "lost_fumbles": 1, "own_rec": 0, "own_rec_yards": 0, "opp_rec": 0, "opp_rec_yards": 0, "out_of_bounds": 0, "forced_fumbles": 0, "own_rec_tds": 0, "opp_rec_tds": 0, "ez_rec_tds": 0}, {"id": "0742d2ea-1cf2-49a6-a150-77ba6e034d8c", "name": "Ryan Fitzpatrick", "jersey": "14", "reference": "00-0023682", "position": "QB", "sr_id": "sr:player:831033", "fumbles": 2, "lost_fumbles": 1, "own_rec": 1, "own_rec_yards": 0, "opp_rec": 0, "opp_rec_yards": 0, "out_of_bounds": 0, "forced_fumbles": 0, "own_rec_tds": 0, "opp_rec_tds": 0, "ez_rec_tds": 0}, {"id": "aaff3798-2b50-47a1-b629-5771454a45d7", "name": "Taco Charlton", "jersey": "96", "reference": "00-0033541", "position": "DE", "sr_id": "sr:player:1129545", "fumbles": 0, "lost_fumbles": 0, "own_rec": 0, "own_rec_yards": 0, "opp_rec": 0, "opp_rec_yards": 0, "out_of_bounds": 0, "forced_fumbles": 1, "own_rec_tds": 0, "opp_rec_tds": 0, "ez_rec_tds": 0}]}, "field_goals": {"totals": {"attempts": 0, "made": 0, "blocked": 0, "yards": 0, "avg_yards": 0.0, "net_attempts": 0}, "players": []}, "extra_points": {"kicks": {"totals": {"attempts": 2, "blocked": 0, "made": 2}, "players": [{"id": "5ffb654f-0de5-424b-aa2f-ad511deb5b51", "name": "Jason Sanders", "jersey": "07", "reference": "00-0034794", "position": "K", "sr_id": "sr:player:1475108", "attempts": 2, "blocked": 0, "made": 2}]}, "conversions": {"totals": {"pass_attempts": 0, "pass_successes": 0, "rush_attempts": 0, "rush_successes": 0, "defense_attempts": 0, "defense_successes": 0, "turnover_successes": 0}, "players": []}}, "defense": {"totals": {"tackles": 46, "assists": 16, "combined": 62, "sacks": 2.0, "sack_yards": 15.0, "interceptions": 1, "passes_defended": 8, "forced_fumbles": 1, "fumble_recoveries": 0, "qb_hits": 7, "tloss": 6.0, "tloss_yards": 22.0, "safeties": 0, "sp_tackles": 2, "sp_assists": 0, "sp_forced_fumbles": 0, "sp_fumble_recoveries": 0, "sp_blocks": 0, "misc_tackles": 3, "misc_assists": 0, "misc_forced_fumbles": 0, "misc_fumble_recoveries": 1, "def_targets": 36, "def_comps": 20, "blitzes": 38, "hurries": 2, "knockdowns": 5, "missed_tackles": 4, "batted_passes": 2}, "players": [{"id": "60d48e85-931c-45dc-b62f-024503a2e09b", "name": "John Jenkins", "jersey": "95", "reference": "00-0030070", "position": "DT", "sr_id": "sr:player:831473", "tackles": 1, "assists": 0, "combined": 1, "sacks": 0.0, "sack_yards": 0.0, "interceptions": 0, "passes_defended": 1, "forced_fumbles": 0, "fumble_recoveries": 0, "qb_hits": 0, "tloss": 0.0, "tloss_yards": 0.0, "safeties": 0, "sp_tackles": 0, "sp_assists": 0, "sp_forced_fumbles": 0, "sp_fumble_recoveries": 0, "sp_blocks": 0, "misc_tackles": 0, "misc_assists": 0, "misc_forced_fumbles": 0, "misc_fumble_recoveries": 0, "def_targets": 0, "def_comps": 0, "blitzes": 0, "hurries": 0, "knockdowns": 0, "missed_tackles": 0, "batted_passes": 1}, {"id": "e6bcb4f1-c2c8-4dd9-b826-af01182875f2", "name": "Xavien Howard", "jersey": "25", "reference": "00-0033050", "position": "CB", "sr_id": "sr:player:987645", "tackles": 1, "assists": 0, "combined": 1, "sacks": 0.0, "sack_yards": 0.0, "interceptions": 1, "passes_defended": 3, "forced_fumbles": 0, "fumble_recoveries": 0, "qb_hits": 0, "tloss": 0.0, "tloss_yards": 0.0, "safeties": 0, "sp_tackles": 0, "sp_assists": 0, "sp_forced_fumbles": 0, "sp_fumble_recoveries": 0, "sp_blocks": 0, "misc_tackles": 0, "misc_assists": 0, "misc_forced_fumbles": 0, "misc_fumble_recoveries": 0, "def_targets": 6, "def_comps": 2, "blitzes": 1, "hurries": 0, "knockdowns": 0, "missed_tackles": 0, "batted_passes": 0}, {"id": "28b0d2fd-18d0-442e-a9ec-70b2f8065ff2", "name": "Vince Biegel", "jersey": "47", "reference": "00-0033939", "position": "LB", "sr_id": "sr:player:1130011", "tackles": 4, "assists": 5, "combined": 9, "sacks": 0.0, "sack_yards": 0.0, "interceptions": 0, "passes_defended": 0, "forced_fumbles": 0, "fumble_recoveries": 0, "qb_hits": 2, "tloss": 1.0, "tloss_yards": 13.0, "safeties": 0, "sp_tackles": 0, "sp_assists": 0, "sp_forced_fumbles": 0, "sp_fumble_recoveries": 0, "sp_blocks": 0, "misc_tackles": 0, "misc_assists": 0, "misc_forced_fumbles": 0, "misc_fumble_recoveries": 0, "def_targets": 3, "def_comps": 2, "blitzes": 6, "hurries": 2, "knockdowns": 2, "missed_tackles": 0, "batted_passes": 0}, {"id": "0742d2ea-1cf2-49a6-a150-77ba6e034d8c", "name": "Ryan Fitzpatrick", "jersey": "14", "reference": "00-0023682", "position": "QB", "sr_id": "sr:player:831033", "tackles": 0, "assists": 0, "combined": 0, "sacks": 0.0, "sack_yards": 0.0, "interceptions": 0, "passes_defended": 0, "forced_fumbles": 0, "fumble_recoveries": 0, "qb_hits": 0, "tloss": 0.0, "tloss_yards": 0.0, "safeties": 0, "sp_tackles": 0, "sp_assists": 0, "sp_forced_fumbles": 0, "sp_fumble_recoveries": 0, "sp_blocks": 0, "misc_tackles": 0, "misc_assists": 0, "misc_forced_fumbles": 0, "misc_fumble_recoveries": 1, "def_targets": 0, "def_comps": 0, "blitzes": 0, "hurries": 0, "knockdowns": 0, "missed_tackles": 0, "batted_passes": 0}, {"id": "6d96bf47-e8c7-4683-8291-74dc426a38cb", "name": "Michael Deiter", "jersey": "63", "reference": "00-0035686", "position": "G", "sr_id": "sr:player:1853496", "tackles": 0, "assists": 0, "combined": 0, "sacks": 0.0, "sack_yards": 0.0, "interceptions": 0, "passes_defended": 0, "forced_fumbles": 0, "fumble_recoveries": 0, "qb_hits": 0, "tloss": 0.0, "tloss_yards": 0.0, "safeties": 0, "sp_tackles": 0, "sp_assists": 0, "sp_forced_fumbles": 0, "sp_fumble_recoveries": 0, "sp_blocks": 0, "misc_tackles": 1, "misc_assists": 0, "misc_forced_fumbles": 0, "misc_fumble_recoveries": 0, "def_targets": 0, "def_comps": 0, "blitzes": 0, "hurries": 0, "knockdowns": 0, "missed_tackles": 0, "batted_passes": 0}, {"id": "8d56094a-7aaa-45fd-bfb1-348f2a994d99", "name": "Jomal Wiltz", "jersey": "33", "reference": "00-0033734", "position": "CB", "sr_id": "sr:player:1134035", "tackles": 1, "assists": 0, "combined": 1, "sacks": 0.0, "sack_yards": 0.0, "interceptions": 0, "passes_defended": 3, "forced_fumbles": 0, "fumble_recoveries": 0, "qb_hits": 0, "tloss": 0.0, "tloss_yards": 0.0, "safeties": 0, "sp_tackles": 0, "sp_assists": 0, "sp_forced_fumbles": 0, "sp_fumble_recoveries": 0, "sp_blocks": 0, "misc_tackles": 0, "misc_assists": 0, "misc_forced_fumbles": 0, "misc_fumble_recoveries": 0, "def_targets": 4, "def_comps": 1, "blitzes": 1, "hurries": 0, "knockdowns": 0, "missed_tackles": 1, "batted_passes": 0}, {"id": "6e6dcc9c-06f5-40fd-9134-d0afd0e349d8", "name": "Davon Godchaux", "jersey": "56", "reference": "00-0033860", "position": "DT", "sr_id": "sr:player:1130111", "tackles": 2, "assists": 2, "combined": 4, "sacks": 0.0, "sack_yards": 0.0, "interceptions": 0, "passes_defended": 0, "forced_fumbles": 0, "fumble_recoveries": 0, "qb_hits": 1, "tloss": 0.0, "tloss_yards": 0.0, "safeties": 0, "sp_tackles": 0, "sp_assists": 0, "sp_forced_fumbles": 0, "sp_fumble_recoveries": 0, "sp_blocks": 0, "misc_tackles": 0, "misc_assists": 0, "misc_forced_fumbles": 0, "misc_fumble_recoveries": 0, "def_targets": 0, "def_comps": 0, "blitzes": 0, "hurries": 0, "knockdowns": 1, "missed_tackles": 0, "batted_passes": 0}, {"id": "5de11f0b-8da9-42ba-9a93-db7f0a58543b", "name": "Jakeem Grant", "jersey": "19", "reference": "00-0032791", "position": "WR", "sr_id": "sr:player:988619", "tackles": 0, "assists": 0, "combined": 0, "sacks": 0.0, "sack_yards": 0.0, "interceptions": 0, "passes_defended": 0, "forced_fumbles": 0, "fumble_recoveries": 0, "qb_hits": 0, "tloss": 0.0, "tloss_yards": 0.0, "safeties": 0, "sp_tackles": 0, "sp_assists": 0, "sp_forced_fumbles": 0, "sp_fumble_recoveries": 0, "sp_blocks": 0, "misc_tackles": 1, "misc_assists": 0, "misc_forced_fumbles": 0, "misc_fumble_recoveries": 0, "def_targets": 0, "def_comps": 0, "blitzes": 0, "hurries": 0, "knockdowns": 0, "missed_tackles": 0, "batted_passes": 0}, {"id": "7f32c3e6-113f-4922-b51d-a1a5a1d43bcf", "name": "Bobby McCain", "jersey": "28", "reference": "00-0031587", "position": "S", "sr_id": "sr:player:835261", "tackles": 1, "assists": 0, "combined": 1, "sacks": 0.0, "sack_yards": 0.0, "interceptions": 0, "passes_defended": 0, "forced_fumbles": 0, "fumble_recoveries": 0, "qb_hits": 0, "tloss": 0.0, "tloss_yards": 0.0, "safeties": 0, "sp_tackles": 0, "sp_assists": 0, "sp_forced_fumbles": 0, "sp_fumble_recoveries": 0, "sp_blocks": 0, "misc_tackles": 0, "misc_assists": 0, "misc_forced_fumbles": 0, "misc_fumble_recoveries": 0, "def_targets": 1, "def_comps": 1, "blitzes": 4, "hurries": 0, "knockdowns": 0, "missed_tackles": 0, "batted_passes": 0}, {"id": "30b045f1-b8e4-4ae9-b062-5181847b508c", "name": "Eric Rowe", "jersey": "21", "reference": "00-0031555", "position": "CB", "sr_id": "sr:player:834669", "tackles": 5, "assists": 0, "combined": 5, "sacks": 0.0, "sack_yards": 0.0, "interceptions": 0, "passes_defended": 1, "forced_fumbles": 0, "fumble_recoveries": 0, "qb_hits": 0, "tloss": 1.0, "tloss_yards": 1.0, "safeties": 0, "sp_tackles": 0, "sp_assists": 0, "sp_forced_fumbles": 0, "sp_fumble_recoveries": 0, "sp_blocks": 0, "misc_tackles": 0, "misc_assists": 0, "misc_forced_fumbles": 0, "misc_fumble_recoveries": 0, "def_targets": 3, "def_comps": 2, "blitzes": 3, "hurries": 0, "knockdowns": 0, "missed_tackles": 1, "batted_passes": 1}, {"id": "aaff3798-2b50-47a1-b629-5771454a45d7", "name": "Taco Charlton", "jersey": "96", "reference": "00-0033541", "position": "DE", "sr_id": "sr:player:1129545", "tackles": 1, "assists": 0, "combined": 1, "sacks": 1.0, "sack_yards": 13.0, "interceptions": 0, "passes_defended": 0, "forced_fumbles": 1, "fumble_recoveries": 0, "qb_hits": 0, "tloss": 0.0, "tloss_yards": 0.0, "safeties": 0, "sp_tackles": 0, "sp_assists": 0, "sp_forced_fumbles": 0, "sp_fumble_recoveries": 0, "sp_blocks": 0, "misc_tackles": 0, "misc_assists": 0, "misc_forced_fumbles": 0, "misc_fumble_recoveries": 0, "def_targets": 0, "def_comps": 0, "blitzes": 0, "hurries": 0, "knockdowns": 0, "missed_tackles": 0, "batted_passes": 0}, {"id": "03e6a751-5206-4f9e-8ffa-f92672f7c159", "name": "Nik Needham", "jersey": "40", "reference": "00-0035346", "position": "DB", "sr_id": "sr:player:1182112", "tackles": 3, "assists": 0, "combined": 3, "sacks": 0.0, "sack_yards": 0.0, "interceptions": 0, "passes_defended": 0, "forced_fumbles": 0, "fumble_recoveries": 0, "qb_hits": 1, "tloss": 0.0, "tloss_yards": 0.0, "safeties": 0, "sp_tackles": 0, "sp_assists": 0, "sp_forced_fumbles": 0, "sp_fumble_recoveries": 0, "sp_blocks": 0, "misc_tackles": 0, "misc_assists": 0, "misc_forced_fumbles": 0, "misc_fumble_recoveries": 0, "def_targets": 4, "def_comps": 3, "blitzes": 3, "hurries": 0, "knockdowns": 1, "missed_tackles": 0, "batted_passes": 0}, {"id": "19403487-1d34-434b-8fc2-a8852167af76", "name": "Walt Aikens", "jersey": "35", "reference": "00-0031307", "position": "S", "sr_id": "sr:player:855748", "tackles": 0, "assists": 0, "combined": 0, "sacks": 0.0, "sack_yards": 0.0, "interceptions": 0, "passes_defended": 0, "forced_fumbles": 0, "fumble_recoveries": 0, "qb_hits": 0, "tloss": 0.0, "tloss_yards": 0.0, "safeties": 0, "sp_tackles": 1, "sp_assists": 0, "sp_forced_fumbles": 0, "sp_fumble_recoveries": 0, "sp_blocks": 0, "misc_tackles": 0, "misc_assists": 0, "misc_forced_fumbles": 0, "misc_fumble_recoveries": 0, "def_targets": 0, "def_comps": 0, "blitzes": 0, "hurries": 0, "knockdowns": 0, "missed_tackles": 0, "batted_passes": 0}, {"id": "18264a0b-cb51-487a-b2cc-f9258f0325f6", "name": "Trent Harris", "jersey": "97", "reference": "00-0034588", "position": "LB", "sr_id": "sr:player:1216342", "tackles": 1, "assists": 1, "combined": 2, "sacks": 0.0, "sack_yards": 0.0, "interceptions": 0, "passes_defended": 0, "forced_fumbles": 0, "fumble_recoveries": 0, "qb_hits": 0, "tloss": 0.0, "tloss_yards": 0.0, "safeties": 0, "sp_tackles": 0, "sp_assists": 0, "sp_forced_fumbles": 0, "sp_fumble_recoveries": 0, "sp_blocks": 0, "misc_tackles": 0, "misc_assists": 0, "misc_forced_fumbles": 0, "misc_fumble_recoveries": 0, "def_targets": 1, "def_comps": 1, "blitzes": 1, "hurries": 0, "knockdowns": 0, "missed_tackles": 0, "batted_passes": 0}, {"id": "bb5e3914-d941-4f05-8c45-bc9c520490ef", "name": "Chris Lammons", "jersey": "30", "reference": "00-0034145", "position": "CB", "sr_id": "sr:player:1475868", "tackles": 1, "assists": 1, "combined": 2, "sacks": 0.0, "sack_yards": 0.0, "interceptions": 0, "passes_defended": 0, "forced_fumbles": 0, "fumble_recoveries": 0, "qb_hits": 0, "tloss": 0.0, "tloss_yards": 0.0, "safeties": 0, "sp_tackles": 0, "sp_assists": 0, "sp_forced_fumbles": 0, "sp_fumble_recoveries": 0, "sp_blocks": 0, "misc_tackles": 0, "misc_assists": 0, "misc_forced_fumbles": 0, "misc_fumble_recoveries": 0, "def_targets": 2, "def_comps": 2, "blitzes": 1, "hurries": 0, "knockdowns": 0, "missed_tackles": 0, "batted_passes": 0}, {"id": "6c640668-de81-49c4-a0da-e367e1747923", "name": "Christian Wilkins", "jersey": "94", "reference": "00-0035231", "position": "DT", "sr_id": "sr:player:1734417", "tackles": 4, "assists": 1, "combined": 5, "sacks": 0.0, "sack_yards": 0.0, "interceptions": 0, "passes_defended": 0, "forced_fumbles": 0, "fumble_recoveries": 0, "qb_hits": 0, "tloss": 0.0, "tloss_yards": 0.0, "safeties": 0, "sp_tackles": 0, "sp_assists": 0, "sp_forced_fumbles": 0, "sp_fumble_recoveries": 0, "sp_blocks": 0, "misc_tackles": 0, "misc_assists": 0, "misc_forced_fumbles": 0, "misc_fumble_recoveries": 0, "def_targets": 0, "def_comps": 0, "blitzes": 0, "hurries": 0, "knockdowns": 0, "missed_tackles": 0, "batted_passes": 0}, {"id": "1012cbe0-7eba-4169-bfca-183a0204e1a7", "name": "Mike Gesicki", "jersey": "88", "reference": "00-0034829", "position": "TE", "sr_id": "sr:player:1218868", "tackles": 0, "assists": 0, "combined": 0, "sacks": 0.0, "sack_yards": 0.0, "interceptions": 0, "passes_defended": 0, "forced_fumbles": 0, "fumble_recoveries": 0, "qb_hits": 0, "tloss": 0.0, "tloss_yards": 0.0, "safeties": 0, "sp_tackles": 0, "sp_assists": 0, "sp_forced_fumbles": 0, "sp_fumble_recoveries": 0, "sp_blocks": 0, "misc_tackles": 1, "misc_assists": 0, "misc_forced_fumbles": 0, "misc_fumble_recoveries": 0, "def_targets": 0, "def_comps": 0, "blitzes": 0, "hurries": 0, "knockdowns": 0, "missed_tackles": 0, "batted_passes": 0}, {"id": "3b4c4797-d35d-4885-93a3-06d85242b522", "name": "Sam Eguavoen", "jersey": "49", "reference": "00-0034902", "position": "LB", "sr_id": "sr:player:1662787", "tackles": 3, "assists": 0, "combined": 3, "sacks": 1.0, "sack_yards": 2.0, "interceptions": 0, "passes_defended": 0, "forced_fumbles": 0, "fumble_recoveries": 0, "qb_hits": 1, "tloss": 1.0, "tloss_yards": 2.0, "safeties": 0, "sp_tackles": 1, "sp_assists": 0, "sp_forced_fumbles": 0, "sp_fumble_recoveries": 0, "sp_blocks": 0, "misc_tackles": 0, "misc_assists": 0, "misc_forced_fumbles": 0, "misc_fumble_recoveries": 0, "def_targets": 1, "def_comps": 0, "blitzes": 11, "hurries": 0, "knockdowns": 0, "missed_tackles": 0, "batted_passes": 0}, {"id": "8aad56a2-0589-4ebc-99f8-b07c5023fd70", "name": "Raekwon McMillan", "jersey": "52", "reference": "00-0033461", "position": "LB", "sr_id": "sr:player:1129753", "tackles": 4, "assists": 3, "combined": 7, "sacks": 0.0, "sack_yards": 0.0, "interceptions": 0, "passes_defended": 0, "forced_fumbles": 0, "fumble_recoveries": 0, "qb_hits": 0, "tloss": 0.0, "tloss_yards": 0.0, "safeties": 0, "sp_tackles": 0, "sp_assists": 0, "sp_forced_fumbles": 0, "sp_fumble_recoveries": 0, "sp_blocks": 0, "misc_tackles": 0, "misc_assists": 0, "misc_forced_fumbles": 0, "misc_fumble_recoveries": 0, "def_targets": 0, "def_comps": 0, "blitzes": 1, "hurries": 0, "knockdowns": 0, "missed_tackles": 1, "batted_passes": 0}, {"id": "b4f07920-56e3-4e9d-b787-014b2f940b0e", "name": "Ken Webster", "jersey": "31", "reference": "00-0035318", "position": "CB", "sr_id": "sr:player:1227536", "tackles": 1, "assists": 1, "combined": 2, "sacks": 0.0, "sack_yards": 0.0, "interceptions": 0, "passes_defended": 0, "forced_fumbles": 0, "fumble_recoveries": 0, "qb_hits": 0, "tloss": 0.0, "tloss_yards": 0.0, "safeties": 0, "sp_tackles": 0, "sp_assists": 0, "sp_forced_fumbles": 0, "sp_fumble_recoveries": 0, "sp_blocks": 0, "misc_tackles": 0, "misc_assists": 0, "misc_forced_fumbles": 0, "misc_fumble_recoveries": 0, "def_targets": 2, "def_comps": 0, "blitzes": 0, "hurries": 0, "knockdowns": 0, "missed_tackles": 0, "batted_passes": 0}, {"id": "ba95b150-fad0-4a8d-b15d-a5e318d95b7f", "name": "Ryan Lewis", "jersey": "24", "reference": "00-0033608", "position": "CB", "sr_id": "sr:player:1131359", "tackles": 5, "assists": 1, "combined": 6, "sacks": 0.0, "sack_yards": 0.0, "interceptions": 0, "passes_defended": 0, "forced_fumbles": 0, "fumble_recoveries": 0, "qb_hits": 0, "tloss": 1.0, "tloss_yards": 1.0, "safeties": 0, "sp_tackles": 0, "sp_assists": 0, "sp_forced_fumbles": 0, "sp_fumble_recoveries": 0, "sp_blocks": 0, "misc_tackles": 0, "misc_assists": 0, "misc_forced_fumbles": 0, "misc_fumble_recoveries": 0, "def_targets": 7, "def_comps": 4, "blitzes": 0, "hurries": 0, "knockdowns": 0, "missed_tackles": 1, "batted_passes": 0}, {"id": "53e7c80e-8bf9-4ab2-ab3e-80cb556ea784", "name": "Jerome Baker", "jersey": "55", "reference": "00-0034797", "position": "LB", "sr_id": "sr:player:1217510", "tackles": 8, "assists": 1, "combined": 9, "sacks": 0.0, "sack_yards": 0.0, "interceptions": 0, "passes_defended": 0, "forced_fumbles": 0, "fumble_recoveries": 0, "qb_hits": 2, "tloss": 2.0, "tloss_yards": 5.0, "safeties": 0, "sp_tackles": 0, "sp_assists": 0, "sp_forced_fumbles": 0, "sp_fumble_recoveries": 0, "sp_blocks": 0, "misc_tackles": 0, "misc_assists": 0, "misc_forced_fumbles": 0, "misc_fumble_recoveries": 0, "def_targets": 2, "def_comps": 2, "blitzes": 6, "hurries": 0, "knockdowns": 1, "missed_tackles": 0, "batted_passes": 0}]}, "efficiency": {"goaltogo": {"attempts": 1, "successes": 1, "pct": 100.0}, "redzone": {"attempts": 2, "successes": 2, "pct": 100.0}, "thirddown": {"attempts": 8, "successes": 3, "pct": 37.5}, "fourthdown": {"attempts": 2, "successes": 0, "pct": 0.0}}, "first_downs": {"pass": 11, "penalty": 1, "rush": 4, "total": 16}, "interceptions": {"return_yards": 0, "returned": 1, "number": 1}, "touchdowns": {"pass": 2, "rush": 0, "total_return": 0, "total": 2, "fumble_return": 0, "int_return": 0, "kick_return": 0, "punt_return": 0, "other": 0}}}, "_comment": "Generation started @ 2019-11-24 20:49:15 +0000 ended @ 2019-11-24 20:49:15 +0000"}